setup.py
src/HW2DA/__init__.py
src/HW2DA/fastHist.py
src/HW2DA/hi.py
src/HW2DA.egg-info/PKG-INFO
src/HW2DA.egg-info/SOURCES.txt
src/HW2DA.egg-info/dependency_links.txt
src/HW2DA.egg-info/requires.txt
src/HW2DA.egg-info/top_level.txt