Metadata-Version: 2.1
Name: HW2DA
Version: 0.0.2
Summary: Package for HW 2
Home-page: UNKNOWN
Author: Eugene Gusarov
Author-email: gen05@yandex-team.ru
License: UNKNOWN
Platform: UNKNOWN
Requires-Python: >=3.6
